Project1-Teste_de_circuitos/counter_N.v
module counter_N(
    input enable,
    input clk,
    input Reset,
    output reg carry_out_N,
    output reg [2:0] count_N
);

    always @(posedge clk or posedge Reset) begin
        if (Reset) begin
            count_N <= 3'd0;
            carry_out_N <= 0;
        end
        else if (enable && (count_N == 3'd5)) begin
            count_N <= 3'd0;
            carry_out_N <= 1;
        end
        else if (enable) begin
            count_N <= count_N + 3'd1;
            carry_out_N <= 0;
        end
    end

endmodule

Project1-Teste_de_circuitos/counter_N_testbench.v
`timescale 1ns / 100ps

module counter_N_testbench;

    reg clk, reset, enable;
    wire carry_out_N;
    wire [2:0] count_N;

    counter_N cnt1 (
        .clk(clk),
        .Reset(reset),
        .enable(enable),
        .carry_out_N(carry_out_N),
        .count_N(count_N)
    );

    initial begin
        $dumpfile("simulation_output.vcd");

        // Dump all signals in the testbench
        $dumpvars(0, counter_N_testbench);
        clk = 0;
    end

    always #1 clk = ~clk;

    initial begin
        clk = 0;
        reset = 1;
        #30 enable = 1;
        #30 reset = 0;
        #30 reset = 1;
        #30 reset = 0;
        #30 $finish;
    end

endmodule

Project1-Teste_de_circuitos/simulation_output.vcd
$date
	Wed Nov 15 18:42:47 2023
$end
$version
	Icarus Verilog
$end
$timescale
	100ps
$end
$scope module counter_N_testbench $end
$var wire 3 ! count_N [2:0] $end
$var wire 1 " carry_out_N $end
$var reg 1 # clk $end
$var reg 1 $ enable $end
$var reg 1 % reset $end
$scope module cnt1 $end
$var wire 1 % Reset $end
$var wire 1 # clk $end
$var wire 1 $ enable $end
$var reg 1 " carry_out_N $end
$var reg 3 & count_N [2:0] $end
$upscope $end
$upscope $end
$enddefinitions $end
$comment Show the parameter values. $end
$dumpall
$end
#0
$dumpvars
b0 &
1%
x$
0#
0"
b0 !
$end
#10
1#
#20
0#
#30
1#
#40
0#
#50
1#
#60
0#
#70
1#
#80
0#
#90
1#
#100
0#
#110
1#
#120
0#
#130
1#
#140
0#
#150
1#
#160
0#
#170
1#
#180
0#
#190
1#
#200
0#
#210
1#
#220
0#
#230
1#
#240
0#
#250
1#
#260
0#
#270
1#
#280
0#
#290
1#
#300
0#
1$
#310
1#
#320
0#
#330
1#
#340
0#
#350
1#
#360
0#
#370
1#
#380
0#
#390
1#
#400
0#
#410
1#
#420
0#
#430
1#
#440
0#
#450
1#
#460
0#
#470
1#
#480
0#
#490
1#
#500
0#
#510
1#
#520
0#
#530
1#
#540
0#
#550
1#
#560
0#
#570
1#
#580
0#
#590
1#
#600
0#
0%
#610
b1 !
b1 &
1#
#620
0#
#630
b10 !
b10 &
1#
#640
0#
#650
b11 !
b11 &
1#
#660
0#
#670
b100 !
b100 &
1#
#680
0#
#690
b101 !
b101 &
1#
#700
0#
#710
1"
b0 !
b0 &
1#
#720
0#
#730
0"
b1 !
b1 &
1#
#740
0#
#750
b10 !
b10 &
1#
#760
0#
#770
b11 !
b11 &
1#
#780
0#
#790
b100 !
b100 &
1#
#800
0#
#810
b101 !
b101 &
1#
#820
0#
#830
1"
b0 !
b0 &
1#
#840
0#
#850
0"
b1 !
b1 &
1#
#860
0#
#870
b10 !
b10 &
1#
#880
0#
#890
b11 !
b11 &
1#
#900
b0 !
b0 &
0#
1%
#910
1#
#920
0#
#930
1#
#940
0#
#950
1#
#960
0#
#970
1#
#980
0#
#990
1#
#1000
0#
#1010
1#
#1020
0#
#1030
1#
#1040
0#
#1050
1#
#1060
0#
#1070
1#
#1080
0#
#1090
1#
#1100
0#
#1110
1#
#1120
0#
#1130
1#
#1140
0#
#1150
1#
#1160
0#
#1170
1#
#1180
0#
#1190
1#
#1200
0#
0%
#1210
b1 !
b1 &
1#
#1220
0#
#1230
b10 !
b10 &
1#
#1240
0#
#1250
b11 !
b11 &
1#
#1260
0#
#1270
b100 !
b100 &
1#
#1280
0#
#1290
b101 !
b101 &
1#
#1300
0#
#1310
1"
b0 !
b0 &
1#
#1320
0#
#1330
0"
b1 !
b1 &
1#
#1340
0#
#1350
b10 !
b10 &
1#
#1360
0#
#1370
b11 !
b11 &
1#
#1380
0#
#1390
b100 !
b100 &
1#
#1400
0#
#1410
b101 !
b101 &
1#
#1420
0#
#1430
1"
b0 !
b0 &
1#
#1440
0#
#1450
0"
b1 !
b1 &
1#
#1460
0#
#1470
b10 !
b10 &
1#
#1480
0#
#1490
b11 !
b11 &
1#
