Project1-Teste_de_circuitos/state_machine_2.v


module state_machine_2( //inputs do block state machine
    input clk, //clock signal
    input start, // start signal
    input reset, // reset signal
    input wire [1:0] start_val, //valor dos flipflops poseedge
    input wire carry_out_N, // carry out N do contadores
    input wire carry_out_M, // cary out M do contador
    input wire [3:0] count_M, // valor do contador M
    output reg OUT, // val OUT
    output reg BIST_END,//BIST end
    output reg Running,// variavel se esta a correr
    output reg [1:0] state, // so para verificar o state no testbench
    output reg [1:0] next_state,//so para verificar o next_state no testbench
    output reg enable_count_N, //enabler do counter N
    output reg enable_count_M// enables do counter ;
);
localparam [1:0] IDLE=0, counting_N=1,
counting_M=2, finish=3;//nome dos estados


always @(posedge clk or posedge reset) begin
    if((reset == 1'b1))begin // reseta sincronamente com o reset, quando reseta muda instantanniamente os valores dos outputs
        state <= IDLE;
        Running = 0;
        OUT = 0;
        BIST_END = 0;
    end
    else begin
        state <= next_state; // update do estado com o clock
    end
end
always @(*) begin
    case (state)
        IDLE: begin
            if((start_val[1:0] == 2'b01) && (Running == 1'b0))begin 
                next_state = counting_N;
                enable_count_N = 1;
                enable_count_M = 0;
                end
            else begin
                next_state = IDLE;
                enable_count_N = 0;
                enable_count_M = 0;
                Running = 0;
                OUT = 0;
                BIST_END = 0;
            end
        end
        counting_N: begin
            enable_count_N = 1;
            Running = 1;
            OUT = 1;
            BIST_END = 0;

            if (carry_out_N == 1'b1) begin
                if(count_M == 4'd12)begin
                    next_state = finish;
                    Running = 0;
                    OUT = 0;
                    BIST_END = 1;
                    enable_count_N = 0;
                    enable_count_M = 1;
                end

                else begin
                    enable_count_M = 1;
                    Running = 1;
                    OUT = 0;
                    BIST_END = 0;
                    next_state = counting_M;
                end
            end
            else begin
                next_state = counting_N;
                enable_count_M = 0;
            end
        end
        counting_M: begin
            next_state = counting_N;
            enable_count_M = 0;
            if ((carry_out_N == 1'b1) &&(count_M == 4'd12)) begin
                next_state = finish;
                enable_count_N = 0;
                enable_count_M = 0;
                Running = 0;
                OUT = 0;
                BIST_END = 1;

            end
            else begin
                next_state = counting_N;
                enable_count_N = 1;
                Running = 1;
                OUT = 1;
                BIST_END = 0;
            end
        end
        finish: begin
            if(start_val[1:0] == 2'b01)begin
                next_state = counting_N;
                enable_count_N = 1;
                enable_count_M = 0;
            end
            else begin 
                next_state = finish;
                enable_count_N = 0;
                enable_count_M = 0;
                Running = 0;
                OUT = 0;
                BIST_END = 1;
            end
        end
        default: next_state = IDLE;
    endcase
end






endmodule

Project1-Teste_de_circuitos/shift_reg.v
module shift_reg(
    input signal,
    input clk,
    input reset,
    output reg [1:0] val
);
    always @(posedge clk or posedge reset)
    begin
        if(reset == 1'b1)begin
            val <= 2'bxx; //xx para ser indeterminado como diz no enunciado
        end
        else begin
            val[1] <= val[0]; //serve para controlar as variaveis do start e reset
            val[0] <= signal;  // basic shift reg
        end
    end
endmodule

Project1-Teste_de_circuitos/counter_M.v
module counter_M(
    input enable, //enable para deixar contar
    input clk, // sincrono com o clock
    input reset, // reset
    output reg carry_out_M,//carry out do M
    output reg [3:0] count_M // M = 12 logo 4 bits
);
   always @(posedge clk or posedge reset) begin // mesma coisa que o N
        if (reset) begin //reset
            count_M <= 4'd0;
            carry_out_M <= 0;
        end
        if(enable)begin
            if(count_M == 4'd12)begin
                count_M <= 4'd0;
                carry_out_M <= 1; //carry out nao e usado mas esta aui pq faz parte de um counter
            end
            else begin
                count_M <= count_M+4'd1;
                carry_out_M <= 0;
            end
        end
    end
endmodule

Project1-Teste_de_circuitos/counter_N.v
module counter_N(//inputs do contador N
    input enable, //enable para controlar quando conta
    input clk, // clock, conta sincronamente co mo clock
    input reset,// reset reseta sincronamente
    output reg carry_out_N,// quando o valor da overflow, nest caso quando chega a 5
    output reg [2:0] count_N //N = 5 valor que se quer contar
);
    always @(posedge clk or posedge reset) begin //so começa sincronamente com o clock
        if (reset) begin //reset
            count_N <= 3'd0; //basic reset reset o valor do cotnador
            carry_out_N <= 0; //basic reset do carry out, reseta o carry out
        end
        if(enable)begin
            if(count_N == 3'd5)begin
                count_N <= 3'd0; // quando existe overflow
                carry_out_N <= 1;// sinal do carry out
            end
            else begin
                count_N <= count_N + 3'd1;//soma do contador
                carry_out_N <= 0;//limpar o valor do carryout
            end
        end
    end

endmodule

Project1-Teste_de_circuitos/top_tb.v
`timescale 1ns / 100ps





module top_tb;


    reg clk, start,reset;
    wire carry_out_M,carry_out_N,enable_count_M,enable_count_N,OUT,BIST_END,Running;
    wire [3:0] count_M;
    wire [2:0] count_N;
    wire [1:0] state,next_state,start_val,reset_val;

    counter_N cnt_N (
        .enable(enable_count_N),
        .clk(clk),
        .carry_out_N(carry_out_N),
        .reset(reset),
        .count_N(count_N)
   );
    counter_M cnt_M (
        .enable(enable_count_M),
        .clk(clk),
        .carry_out_M(carry_out_M),
        .reset(reset),
        .count_M(count_M)
    );

    shift_reg start_shift (
        .signal(start),
        .clk(clk),
        .val(start_val),
        .reset(reset)
    );
 
    state_machine_2 STATE2(
        .clk(clk),
        .reset(reset),
        .start(start),
        .Running(Running),
        .OUT(OUT),
        .BIST_END(BIST_END),
        .enable_count_M(enable_count_M),
        .enable_count_N(enable_count_N),
        .carry_out_M(carry_out_M),
        .carry_out_N(carry_out_N),
        .state(state),
        .next_state(next_state),
        .start_val(start_val),
        .count_M(count_M)
    );  


    initial begin
        $dumpfile("simulation_output.vcd");
        // Dump all signals in the testbench
        $dumpvars(0, clk, start,OUT,reset,BIST_END,Running,start_val,next_state,state,carry_out_M,carry_out_N,enable_count_M,enable_count_N,count_N,count_M); // Add signals to be dumped
        clk = 0;
        start = 0;
        reset = 1;
        #3 start = 1;
        #4 reset = 0;
        #3 start = 1;
        #8 start = 0;
        #8 start = 1;
        #70 start = 0;
        #3 start = 1;
        #3start = 0;
        #3 start = 1;
        #3 start = 0;
        #3 start = 1;
        #33 start = 0;
        #3 start = 0;
        #400 $finish;
    end
    always #2 clk = ~clk;
endmodule

Project1-Teste_de_circuitos/simulation_output.vcd
$date
	Mon Nov 20 22:03:38 2023
$end
$version
	Icarus Verilog
$end
$timescale
	100ps
$end
$scope module top_tb $end
$var reg 1 ! clk $end
$upscope $end
$scope module top_tb $end
$var reg 1 " start $end
$upscope $end
$scope module top_tb $end
$var wire 1 # OUT $end
$upscope $end
$scope module top_tb $end
$var reg 1 $ reset $end
$upscope $end
$scope module top_tb $end
$var wire 1 % BIST_END $end
$upscope $end
$scope module top_tb $end
$var wire 1 & Running $end
$upscope $end
$scope module top_tb $end
$var wire 2 ' start_val [1:0] $end
$upscope $end
$scope module top_tb $end
$var wire 2 ( next_state [1:0] $end
$upscope $end
$scope module top_tb $end
$var wire 2 ) state [1:0] $end
$upscope $end
$scope module top_tb $end
$var wire 1 * carry_out_M $end
$upscope $end
$scope module top_tb $end
$var wire 1 + carry_out_N $end
$upscope $end
$scope module top_tb $end
$var wire 1 , enable_count_M $end
$upscope $end
$scope module top_tb $end
$var wire 1 - enable_count_N $end
$upscope $end
$scope module top_tb $end
$var wire 3 . count_N [2:0] $end
$upscope $end
$scope module top_tb $end
$var wire 4 / count_M [3:0] $end
$upscope $end
$enddefinitions $end
$comment Show the parameter values. $end
$dumpall
$end
#0
$dumpvars
b0 /
b0 .
0-
0,
0+
0*
b0 )
b0 (
bx '
0&
0%
1$
0#
0"
0!
$end
#20
1!
#30
1"
#40
0!
#60
1!
#70
0$
#80
0!
#100
bx1 '
1!
#120
0!
#140
b11 '
1!
#160
0!
#180
b10 '
1!
0"
#200
0!
#220
b0 '
1!
#240
0!
#260
1-
b1 (
b1 '
1!
1"
#280
0!
#300
1#
1&
b1 .
b11 '
b1 )
1!
#320
0!
#340
b10 .
1!
#360
0!
#380
b11 .
1!
#400
0!
#420
b100 .
1!
#440
0!
#460
b101 .
1!
#480
0!
#500
b10 (
0#
1,
1+
b0 .
1!
#520
0!
#540
1#
0,
b1 (
0+
b1 .
b1 /
b10 )
1!
#560
0!
#580
b1 )
b10 .
1!
#600
0!
#620
b11 .
1!
#640
0!
#660
b100 .
1!
#680
0!
#700
b101 .
1!
#720
0!
#740
b10 (
0#
1,
1+
b0 .
1!
#760
0!
#780
1#
0,
b1 (
0+
b1 .
b10 /
b10 )
1!
#800
0!
#820
b1 )
b10 .
1!
#840
0!
#860
b11 .
1!
#880
0!
#900
b100 .
1!
#920
0!
#940
b101 .
1!
#960
0!
0"
#980
b10 (
0#
1,
b10 '
1+
b0 .
1!
#990
1"
#1000
0!
#1020
1#
0,
b1 (
0+
b1 .
b11 /
b0 '
b10 )
1!
0"
#1040
0!
#1050
1"
#1060
b1 )
b1 '
b10 .
1!
#1080
0!
0"
#1100
b11 .
b10 '
1!
#1110
1"
#1120
0!
#1140
b1 '
b100 .
1!
#1160
0!
#1180
b101 .
b11 '
1!
#1200
0!
#1220
b10 (
0#
1,
1+
b0 .
1!
#1240
0!
#1260
1#
0,
b1 (
0+
b1 .
b100 /
b10 )
1!
#1280
0!
#1300
b1 )
b10 .
1!
#1320
0!
#1340
b11 .
1!
#1360
0!
#1380
b100 .
1!
#1400
0!
#1420
b101 .
1!
#1440
0!
0"
#1460
b10 (
0#
1,
b10 '
1+
b0 .
1!
#1480
0!
#1500
1#
0,
b1 (
0+
b1 .
b101 /
b0 '
b10 )
1!
#1520
0!
#1540
b1 )
b10 .
1!
#1560
0!
#1580
b11 .
1!
#1600
0!
#1620
b100 .
1!
#1640
0!
#1660
b101 .
1!
#1680
0!
#1700
b10 (
0#
1,
1+
b0 .
1!
#1720
0!
#1740
1#
0,
b1 (
0+
b1 .
b110 /
b10 )
1!
#1760
0!
#1780
b1 )
b10 .
1!
#1800
0!
#1820
b11 .
1!
#1840
0!
#1860
b100 .
1!
#1880
0!
#1900
b101 .
1!
#1920
0!
#1940
b10 (
0#
1,
1+
b0 .
1!
#1960
0!
#1980
1#
0,
b1 (
0+
b1 .
b111 /
b10 )
1!
#2000
0!
#2020
b1 )
b10 .
1!
#2040
0!
#2060
b11 .
1!
#2080
0!
#2100
b100 .
1!
#2120
0!
#2140
b101 .
1!
#2160
0!
#2180
b10 (
0#
1,
1+
b0 .
1!
#2200
0!
#2220
1#
0,
b1 (
0+
b1 .
b1000 /
b10 )
1!
#2240
0!
#2260
b1 )
b10 .
1!
#2280
0!
#2300
b11 .
1!
#2320
0!
#2340
b100 .
1!
#2360
0!
#2380
b101 .
1!
#2400
0!
#2420
b10 (
0#
1,
1+
b0 .
1!
#2440
0!
#2460
1#
0,
b1 (
0+
b1 .
b1001 /
b10 )
1!
#2480
0!
#2500
b1 )
b10 .
1!
#2520
0!
#2540
b11 .
1!
#2560
0!
#2580
b100 .
1!
#2600
0!
#2620
b101 .
1!
#2640
0!
#2660
b10 (
0#
1,
1+
b0 .
1!
#2680
0!
#2700
1#
0,
b1 (
0+
b1 .
b1010 /
b10 )
1!
#2720
0!
#2740
b1 )
b10 .
1!
#2760
0!
#2780
b11 .
1!
#2800
0!
#2820
b100 .
1!
#2840
0!
#2860
b101 .
1!
#2880
0!
#2900
b10 (
0#
1,
1+
b0 .
1!
#2920
0!
#2940
1#
0,
b1 (
0+
b1 .
b1011 /
b10 )
1!
#2960
0!
#2980
b1 )
b10 .
1!
#3000
0!
#3020
b11 .
1!
#3040
0!
#3060
b100 .
1!
#3080
0!
#3100
b101 .
1!
#3120
0!
#3140
b10 (
0#
1,
1+
b0 .
1!
#3160
0!
#3180
1#
0,
b1 (
0+
b1 .
b1100 /
b10 )
1!
#3200
0!
#3220
b1 )
b10 .
1!
#3240
0!
#3260
b11 .
1!
#3280
0!
#3300
b100 .
1!
#3320
0!
#3340
b101 .
1!
#3360
0!
#3380
1,
0-
1%
0#
0&
b11 (
1+
b0 .
1!
#3400
0!
#3420
0,
1*
b0 /
b11 )
1!
